<annotation>
  <folder>images</folder>
  <filename>Line 2_CNav_1000_48000_1500_48500.jpg</filename>
  <size>
    <width>500</width>
    <height>500</height>
    <depth>3</depth>
  </size>
  <object>
    <name>shadow</name>
    <pose>Unspecified</pose>
    <truncated>0</truncated>
    <difficult>0</difficult>
    <bndbox>
      <xmin>203</xmin>
      <ymin>481</ymin>
      <xmax>375</xmax>
      <ymax>490</ymax>
    </bndbox>
  </object>
  <object>
    <name>object</name>
    <pose>Unspecified</pose>
    <truncated>0</truncated>
    <difficult>0</difficult>
    <bndbox>
      <xmin>171</xmin>
      <ymin>481</ymin>
      <xmax>234</xmax>
      <ymax>490</ymax>
    </bndbox>
  </object>
  <object>
    <name>shadow</name>
    <pose>Unspecified</pose>
    <truncated>0</truncated>
    <difficult>0</difficult>
    <bndbox>
      <xmin>223</xmin>
      <ymin>82</ymin>
      <xmax>292</xmax>
      <ymax>85</ymax>
    </bndbox>
  </object>
  <object>
    <name>object</name>
    <pose>Unspecified</pose>
    <truncated>0</truncated>
    <difficult>0</difficult>
    <bndbox>
      <xmin>203</xmin>
      <ymin>82</ymin>
      <xmax>244</xmax>
      <ymax>85</ymax>
    </bndbox>
  </object>
</annotation>