<annotation>
  <folder>images</folder>
  <filename>Line 2_CNav_6000_11500_6500_12000.jpg</filename>
  <size>
    <width>500</width>
    <height>500</height>
    <depth>3</depth>
  </size>
  <object>
    <name>shadow</name>
    <pose>Unspecified</pose>
    <truncated>0</truncated>
    <difficult>0</difficult>
    <bndbox>
      <xmin>167</xmin>
      <ymin>432</ymin>
      <xmax>287</xmax>
      <ymax>441</ymax>
    </bndbox>
  </object>
  <object>
    <name>object</name>
    <pose>Unspecified</pose>
    <truncated>0</truncated>
    <difficult>0</difficult>
    <bndbox>
      <xmin>241</xmin>
      <ymin>432</ymin>
      <xmax>334</xmax>
      <ymax>441</ymax>
    </bndbox>
  </object>
  <object>
    <name>shadow</name>
    <pose>Unspecified</pose>
    <truncated>0</truncated>
    <difficult>0</difficult>
    <bndbox>
      <xmin>436</xmin>
      <ymin>153</ymin>
      <xmax>494</xmax>
      <ymax>162</ymax>
    </bndbox>
  </object>
  <object>
    <name>object</name>
    <pose>Unspecified</pose>
    <truncated>0</truncated>
    <difficult>0</difficult>
    <bndbox>
      <xmin>457</xmin>
      <ymin>153</ymin>
      <xmax>500</xmax>
      <ymax>162</ymax>
    </bndbox>
  </object>
</annotation>