<?xml version="1.0" ?>
<annotation>
  <folder>images</folder>
  <filename>Line 2_CNav_8000_47500_8500_48000.jpg</filename>
  <size>
    <width>500</width>
    <height>500</height>
    <depth>3</depth>
  </size>
  <object>
    <name>object_1</name>
    <pose>Unspecified</pose>
    <truncated>0</truncated>
    <difficult>0</difficult>
    <bndbox>
      <xmin>82</xmin>
      <ymin>424</ymin>
      <xmax>297</xmax>
      <ymax>443</ymax>
    </bndbox>
  </object>
  <object>
    <name>object</name>
    <pose>Unspecified</pose>
    <truncated>0</truncated>
    <difficult>0</difficult>
    <bndbox>
      <xmin>3</xmin>
      <ymin>424</ymin>
      <xmax>160</xmax>
      <ymax>443</ymax>
    </bndbox>
  </object>
  <object>
    <name>object_1</name>
    <pose>Unspecified</pose>
    <truncated>0</truncated>
    <difficult>0</difficult>
    <bndbox>
      <xmin>104</xmin>
      <ymin>350</ymin>
      <xmax>320</xmax>
      <ymax>369</ymax>
    </bndbox>
  </object>
  <object>
    <name>object</name>
    <pose>Unspecified</pose>
    <truncated>0</truncated>
    <difficult>0</difficult>
    <bndbox>
      <xmin>51</xmin>
      <ymin>350</ymin>
      <xmax>156</xmax>
      <ymax>369</ymax>
    </bndbox>
  </object>
  <object>
    <name>object_1</name>
    <pose>Unspecified</pose>
    <truncated>0</truncated>
    <difficult>0</difficult>
    <bndbox>
      <xmin>81</xmin>
      <ymin>483</ymin>
      <xmax>500</xmax>
      <ymax>492</ymax>
    </bndbox>
  </object>
  <object>
    <name>object</name>
    <pose>Unspecified</pose>
    <truncated>0</truncated>
    <difficult>0</difficult>
    <bndbox>
      <xmin>50</xmin>
      <ymin>483</ymin>
      <xmax>113</xmax>
      <ymax>492</ymax>
    </bndbox>
  </object>
  <object>
    <name>object_1</name>
    <pose>Unspecified</pose>
    <truncated>0</truncated>
    <difficult>0</difficult>
    <bndbox>
      <xmin>343</xmin>
      <ymin>345</ymin>
      <xmax>500</xmax>
      <ymax>352</ymax>
    </bndbox>
  </object>
  <object>
    <name>object</name>
    <pose>Unspecified</pose>
    <truncated>0</truncated>
    <difficult>0</difficult>
    <bndbox>
      <xmin>322</xmin>
      <ymin>345</ymin>
      <xmax>363</xmax>
      <ymax>352</ymax>
    </bndbox>
  </object>
  <object>
    <name>object_1</name>
    <pose>Unspecified</pose>
    <truncated>0</truncated>
    <difficult>0</difficult>
    <bndbox>
      <xmin>126</xmin>
      <ymin>326</ymin>
      <xmax>290</xmax>
      <ymax>331</ymax>
    </bndbox>
  </object>
  <object>
    <name>object</name>
    <pose>Unspecified</pose>
    <truncated>0</truncated>
    <difficult>0</difficult>
    <bndbox>
      <xmin>99</xmin>
      <ymin>326</ymin>
      <xmax>152</xmax>
      <ymax>331</ymax>
    </bndbox>
  </object>
  <object>
    <name>object</name>
    <pose>Unspecified</pose>
    <truncated>0</truncated>
    <difficult>0</difficult>
    <bndbox>
      <xmin>457</xmin>
      <ymin>94</ymin>
      <xmax>500</xmax>
      <ymax>99</ymax>
    </bndbox>
  </object>
  <object>
    <name>object_1</name>
    <pose>Unspecified</pose>
    <truncated>0</truncated>
    <difficult>0</difficult>
    <bndbox>
      <xmin>0</xmin>
      <ymin>177</ymin>
      <xmax>76</xmax>
      <ymax>180</ymax>
    </bndbox>
  </object>
</annotation>
