<annotation>
    <folder>object_detection</folder>
    <filename>Line 2_CNav_6500_32500_7000_33000.jpg</filename>
    <path>C:\seabed\d_adapt\TransferLearningForSonarData\examples\domain_adaptation\object_detection\Line 2_CNav_6500_32500_7000_33000.jpg</path>
    <source>
        <database>Unknown</database>
    </source>
    <size>
        <width>500</width>
        <height>500</height>
        <depth>3</depth>
    </size>
    <segmented>0</segmented>
    <object>
        <name>shadow</name>
        <pose>Unspecified</pose>
        <truncated>0</truncated>
        <difficult>0</difficult>
        <bndbox>
            <xmin>287.0</xmin>
            <ymin>141.06913209068807</ymin>
            <xmax>400.6182888320491</xmax>
            <ymax>154.9308679093083</ymax>
        </bndbox>
    </object>    <object>
        <name>rock</name>
        <pose>Unspecified</pose>
        <truncated>0</truncated>
        <difficult>0</difficult>
        <bndbox>
            <xmin>281.79166674238786</xmin>
            <ymin>141.06913209068807</ymin>
            <xmax>292.20833325761214</xmax>
            <ymax>154.9308679093083</ymax>
        </bndbox>
    </object>    <object>
        <name>shadow</name>
        <pose>Unspecified</pose>
        <truncated>0</truncated>
        <difficult>0</difficult>
        <bndbox>
            <xmin>81.0</xmin>
            <ymin>256.6226097414874</ymin>
            <xmax>233.39224055387876</xmax>
            <ymax>265.3773902585126</ymax>
        </bndbox>
    </object>    <object>
        <name>rock</name>
        <pose>Unspecified</pose>
        <truncated>0</truncated>
        <difficult>0</difficult>
        <bndbox>
            <xmin>44.541667196715025</xmin>
            <ymin>256.6226097414874</ymin>
            <xmax>117.45833280328588</xmax>
            <ymax>265.3773902585126</ymax>
        </bndbox>
    </object>    <object>
        <name>shadow</name>
        <pose>Unspecified</pose>
        <truncated>0</truncated>
        <difficult>0</difficult>
        <bndbox>
            <xmin>195.0</xmin>
            <ymin>494.9873922630286</ymin>
            <xmax>252.0810088774706</xmax>
            <ymax>500.0</ymax>
        </bndbox>
    </object>    <object>
        <name>rock</name>
        <pose>Unspecified</pose>
        <truncated>0</truncated>
        <difficult>0</difficult>
        <bndbox>
            <xmin>158.54166719671503</xmin>
            <ymin>494.9873922630286</ymin>
            <xmax>231.45833280328588</xmax>
            <ymax>500.0</ymax>
        </bndbox>
    </object>    <object>
        <name>shadow</name>
        <pose>Unspecified</pose>
        <truncated>0</truncated>
        <difficult>0</difficult>
        <bndbox>
            <xmin>146.0</xmin>
            <ymin>445.7169573061183</ymin>
            <xmax>284.0629320511498</xmax>
            <ymax>452.283042693889</ymax>
        </bndbox>
    </object>    <object>
        <name>rock</name>
        <pose>Unspecified</pose>
        <truncated>0</truncated>
        <difficult>0</difficult>
        <bndbox>
            <xmin>125.16666696955144</xmin>
            <ymin>445.7169573061183</ymin>
            <xmax>166.83333303044856</xmax>
            <ymax>452.283042693889</ymax>
        </bndbox>
    </object>    <object>
        <name>shadow</name>
        <pose>Unspecified</pose>
        <truncated>0</truncated>
        <difficult>0</difficult>
        <bndbox>
            <xmin>0.0</xmin>
            <ymin>8.081739827659476</ymin>
            <xmax>54.16742701169369</xmax>
            <ymax>13.918260172340524</ymax>
        </bndbox>
    </object>    <object>
        <name>rock</name>
        <pose>Unspecified</pose>
        <truncated>0</truncated>
        <difficult>0</difficult>
        <bndbox>
            <xmin>0.0</xmin>
            <ymin>8.081739827659476</ymin>
            <xmax>10.041666288060696</xmax>
            <ymax>13.918260172340524</ymax>
        </bndbox>
    </object>
</annotation>
