<annotation>
    <folder>object_detection</folder>
    <filename>Line 2_CNav_5000_3500_5500_4000.jpg</filename>
    <path>C:\seabed\d_adapt\TransferLearningForSonarData\examples\domain_adaptation\object_detection\Line 2_CNav_5000_3500_5500_4000.jpg</path>
    <source>
        <database>Unknown</database>
    </source>
    <size>
        <width>500</width>
        <height>500</height>
        <depth>3</depth>
    </size>
    <segmented>0</segmented>
    <object>
        <name>shadow</name>
        <pose>Unspecified</pose>
        <truncated>0</truncated>
        <difficult>0</difficult>
        <bndbox>
            <xmin>0.0</xmin>
            <ymin>329.9747845260613</ymin>
            <xmax>78.28785208906174</xmax>
            <ymax>346.02521547393917</ymax>
        </bndbox>
    </object>    <object>
        <name>rock</name>
        <pose>Unspecified</pose>
        <truncated>0</truncated>
        <difficult>0</difficult>
        <bndbox>
            <xmin>0.0</xmin>
            <ymin>329.9747845260613</ymin>
            <xmax>43.0833325761223</xmax>
            <ymax>346.02521547393917</ymax>
        </bndbox>
    </object>    <object>
        <name>shadow</name>
        <pose>Unspecified</pose>
        <truncated>0</truncated>
        <difficult>0</difficult>
        <bndbox>
            <xmin>34.0</xmin>
            <ymin>81.62260974148785</ymin>
            <xmax>219.6782368603035</xmax>
            <ymax>90.37739025851215</ymax>
        </bndbox>
    </object>    <object>
        <name>rock</name>
        <pose>Unspecified</pose>
        <truncated>0</truncated>
        <difficult>0</difficult>
        <bndbox>
            <xmin>2.7500004543271643</xmin>
            <ymin>81.62260974148785</ymin>
            <xmax>65.24999954567284</xmax>
            <ymax>90.37739025851215</ymax>
        </bndbox>
    </object>    <object>
        <name>shadow</name>
        <pose>Unspecified</pose>
        <truncated>0</truncated>
        <difficult>0</difficult>
        <bndbox>
            <xmin>0.0</xmin>
            <ymin>416.08173982765857</ymin>
            <xmax>150.63342658100646</xmax>
            <ymax>421.91826017234143</ymax>
        </bndbox>
    </object>    <object>
        <name>shadow</name>
        <pose>Unspecified</pose>
        <truncated>0</truncated>
        <difficult>0</difficult>
        <bndbox>
            <xmin>0.0</xmin>
            <ymin>418.08173982765857</ymin>
            <xmax>139.14833706841728</xmax>
            <ymax>423.91826017234143</ymax>
        </bndbox>
    </object>
</annotation>
