<annotation>
    <folder>object_detection</folder>
    <filename>Line 2_CNav_3500_6000_4000_6500.jpg</filename>
    <path>C:\seabed\d_adapt\TransferLearningForSonarData\examples\domain_adaptation\object_detection\Line 2_CNav_3500_6000_4000_6500.jpg</path>
    <source>
        <database>Unknown</database>
    </source>
    <size>
        <width>500</width>
        <height>500</height>
        <depth>3</depth>
    </size>
    <segmented>0</segmented>
    <object>
        <name>shadow</name>
        <pose>Unspecified</pose>
        <truncated>0</truncated>
        <difficult>0</difficult>
        <bndbox>
            <xmin>0.0</xmin>
            <ymin>453.33956704760385</ymin>
            <xmax>213.75841156945899</xmax>
            <ymax>468.66043295239615</ymax>
        </bndbox>
    </object>    <object>
        <name>shadow</name>
        <pose>Unspecified</pose>
        <truncated>0</truncated>
        <difficult>0</difficult>
        <bndbox>
            <xmin>472.0</xmin>
            <ymin>139.70434956914687</ymin>
            <xmax>500.0</xmax>
            <ymax>154.29565043085404</ymax>
        </bndbox>
    </object>    <object>
        <name>rock</name>
        <pose>Unspecified</pose>
        <truncated>0</truncated>
        <difficult>0</difficult>
        <bndbox>
            <xmin>456.3750002271636</xmin>
            <ymin>139.70434956914687</ymin>
            <xmax>487.6249997728364</xmax>
            <ymax>154.29565043085404</ymax>
        </bndbox>
    </object>    <object>
        <name>shadow</name>
        <pose>Unspecified</pose>
        <truncated>0</truncated>
        <difficult>0</difficult>
        <bndbox>
            <xmin>445.0</xmin>
            <ymin>180.06913209068898</ymin>
            <xmax>500.0</xmax>
            <ymax>193.93086790931102</ymax>
        </bndbox>
    </object>    <object>
        <name>rock</name>
        <pose>Unspecified</pose>
        <truncated>0</truncated>
        <difficult>0</difficult>
        <bndbox>
            <xmin>377.29166765104173</xmin>
            <ymin>180.06913209068898</ymin>
            <xmax>500.0</xmax>
            <ymax>193.93086790931102</ymax>
        </bndbox>
    </object>    <object>
        <name>shadow</name>
        <pose>Unspecified</pose>
        <truncated>0</truncated>
        <difficult>0</difficult>
        <bndbox>
            <xmin>33.0</xmin>
            <ymin>69.79869713377411</ymin>
            <xmax>95.26926482319004</xmax>
            <ymax>82.20130286622498</ymax>
        </bndbox>
    </object>    <object>
        <name>rock</name>
        <pose>Unspecified</pose>
        <truncated>0</truncated>
        <difficult>0</difficult>
        <bndbox>
            <xmin>0.0</xmin>
            <ymin>69.79869713377411</ymin>
            <xmax>74.66666606089711</xmax>
            <ymax>82.20130286622498</ymax>
        </bndbox>
    </object>    <object>
        <name>shadow</name>
        <pose>Unspecified</pose>
        <truncated>0</truncated>
        <difficult>0</difficult>
        <bndbox>
            <xmin>1.0</xmin>
            <ymin>468.16347965531713</ymin>
            <xmax>500.0</xmax>
            <ymax>479.83652034468287</ymax>
        </bndbox>
    </object>    <object>
        <name>rock</name>
        <pose>Unspecified</pose>
        <truncated>0</truncated>
        <difficult>0</difficult>
        <bndbox>
            <xmin>0.0</xmin>
            <ymin>468.16347965531713</ymin>
            <xmax>68.70833234895827</xmax>
            <ymax>479.83652034468287</ymax>
        </bndbox>
    </object>    <object>
        <name>rock</name>
        <pose>Unspecified</pose>
        <truncated>0</truncated>
        <difficult>0</difficult>
        <bndbox>
            <xmin>462.541667196715</xmin>
            <ymin>13.528262176860153</ymin>
            <xmax>500.0</xmax>
            <ymax>24.471737823140757</ymax>
        </bndbox>
    </object>    <object>
        <name>shadow</name>
        <pose>Unspecified</pose>
        <truncated>0</truncated>
        <difficult>0</difficult>
        <bndbox>
            <xmin>413.0</xmin>
            <ymin>323.6226097414883</ymin>
            <xmax>500.0</xmax>
            <ymax>332.3773902585126</ymax>
        </bndbox>
    </object>    <object>
        <name>rock</name>
        <pose>Unspecified</pose>
        <truncated>0</truncated>
        <difficult>0</difficult>
        <bndbox>
            <xmin>366.1250006814903</xmin>
            <ymin>323.6226097414883</ymin>
            <xmax>459.87499931850925</xmax>
            <ymax>332.3773902585126</ymax>
        </bndbox>
    </object>    <object>
        <name>shadow</name>
        <pose>Unspecified</pose>
        <truncated>0</truncated>
        <difficult>0</difficult>
        <bndbox>
            <xmin>342.0</xmin>
            <ymin>473.9873922630304</ymin>
            <xmax>500.0</xmax>
            <ymax>482.0126077369696</ymax>
        </bndbox>
    </object>    <object>
        <name>rock</name>
        <pose>Unspecified</pose>
        <truncated>0</truncated>
        <difficult>0</difficult>
        <bndbox>
            <xmin>310.75000045432716</xmin>
            <ymin>473.9873922630304</ymin>
            <xmax>373.2499995456733</xmax>
            <ymax>482.0126077369696</ymax>
        </bndbox>
    </object>    <object>
        <name>shadow</name>
        <pose>Unspecified</pose>
        <truncated>0</truncated>
        <difficult>0</difficult>
        <bndbox>
            <xmin>6.0</xmin>
            <ymin>219.35217478457344</ymin>
            <xmax>246.86815689171453</xmax>
            <ymax>226.64782521542656</ymax>
        </bndbox>
    </object>    <object>
        <name>rock</name>
        <pose>Unspecified</pose>
        <truncated>0</truncated>
        <difficult>0</difficult>
        <bndbox>
            <xmin>0.0</xmin>
            <ymin>219.35217478457344</ymin>
            <xmax>32.04166628806115</xmax>
            <ymax>226.64782521542656</ymax>
        </bndbox>
    </object>    <object>
        <name>shadow</name>
        <pose>Unspecified</pose>
        <truncated>0</truncated>
        <difficult>0</difficult>
        <bndbox>
            <xmin>353.0</xmin>
            <ymin>290.71695730611555</ymin>
            <xmax>500.0</xmax>
            <ymax>297.28304269388354</ymax>
        </bndbox>
    </object>    <object>
        <name>rock</name>
        <pose>Unspecified</pose>
        <truncated>0</truncated>
        <difficult>0</difficult>
        <bndbox>
            <xmin>311.33333393910243</xmin>
            <ymin>290.71695730611555</ymin>
            <xmax>394.6666660608971</xmax>
            <ymax>297.28304269388354</ymax>
        </bndbox>
    </object>    <object>
        <name>shadow</name>
        <pose>Unspecified</pose>
        <truncated>0</truncated>
        <difficult>0</difficult>
        <bndbox>
            <xmin>0.0</xmin>
            <ymin>344.08173982765857</ymin>
            <xmax>244.67195682574493</xmax>
            <ymax>349.91826017234143</ymax>
        </bndbox>
    </object>    <object>
        <name>shadow</name>
        <pose>Unspecified</pose>
        <truncated>0</truncated>
        <difficult>0</difficult>
        <bndbox>
            <xmin>33.0</xmin>
            <ymin>165.4465223492016</ymin>
            <xmax>156.50315901367685</xmax>
            <ymax>170.55347765079932</ymax>
        </bndbox>
    </object>    <object>
        <name>rock</name>
        <pose>Unspecified</pose>
        <truncated>0</truncated>
        <difficult>0</difficult>
        <bndbox>
            <xmin>6.958333711939304</xmin>
            <ymin>165.4465223492016</ymin>
            <xmax>59.04166628806115</xmax>
            <ymax>170.55347765079932</ymax>
        </bndbox>
    </object>    <object>
        <name>shadow</name>
        <pose>Unspecified</pose>
        <truncated>0</truncated>
        <difficult>0</difficult>
        <bndbox>
            <xmin>391.0</xmin>
            <ymin>272.4465223492016</ymin>
            <xmax>500.0</xmax>
            <ymax>277.5534776507993</ymax>
        </bndbox>
    </object>    <object>
        <name>rock</name>
        <pose>Unspecified</pose>
        <truncated>0</truncated>
        <difficult>0</difficult>
        <bndbox>
            <xmin>385.79166674238786</xmin>
            <ymin>272.4465223492016</ymin>
            <xmax>396.20833325761214</xmax>
            <ymax>277.5534776507993</ymax>
        </bndbox>
    </object>    <object>
        <name>shadow</name>
        <pose>Unspecified</pose>
        <truncated>0</truncated>
        <difficult>0</difficult>
        <bndbox>
            <xmin>348.0</xmin>
            <ymin>290.4465223492016</ymin>
            <xmax>500.0</xmax>
            <ymax>295.5534776507993</ymax>
        </bndbox>
    </object>    <object>
        <name>rock</name>
        <pose>Unspecified</pose>
        <truncated>0</truncated>
        <difficult>0</difficult>
        <bndbox>
            <xmin>316.75000045432716</xmin>
            <ymin>290.4465223492016</ymin>
            <xmax>379.2499995456733</xmax>
            <ymax>295.5534776507993</ymax>
        </bndbox>
    </object>    <object>
        <name>shadow</name>
        <pose>Unspecified</pose>
        <truncated>0</truncated>
        <difficult>0</difficult>
        <bndbox>
            <xmin>245.0</xmin>
            <ymin>317.4465223492016</ymin>
            <xmax>308.7723412252344</xmax>
            <ymax>322.5534776507993</ymax>
        </bndbox>
    </object>    <object>
        <name>rock</name>
        <pose>Unspecified</pose>
        <truncated>0</truncated>
        <difficult>0</difficult>
        <bndbox>
            <xmin>224.16666696955144</xmin>
            <ymin>317.4465223492016</ymin>
            <xmax>265.833333030449</xmax>
            <ymax>322.5534776507993</ymax>
        </bndbox>
    </object>    <object>
        <name>shadow</name>
        <pose>Unspecified</pose>
        <truncated>0</truncated>
        <difficult>0</difficult>
        <bndbox>
            <xmin>0.0</xmin>
            <ymin>152.8113048707437</ymin>
            <xmax>322.8202168076882</xmax>
            <ymax>157.1886951292554</ymax>
        </bndbox>
    </object>    <object>
        <name>shadow</name>
        <pose>Unspecified</pose>
        <truncated>0</truncated>
        <difficult>0</difficult>
        <bndbox>
            <xmin>1.0</xmin>
            <ymin>273.1760873922867</ymin>
            <xmax>120.65490742822294</xmax>
            <ymax>276.8239126077133</ymax>
        </bndbox>
    </object>    <object>
        <name>rock</name>
        <pose>Unspecified</pose>
        <truncated>0</truncated>
        <difficult>0</difficult>
        <bndbox>
            <xmin>0.0</xmin>
            <ymin>273.1760873922867</ymin>
            <xmax>27.04166628806115</xmax>
            <ymax>276.8239126077133</ymax>
        </bndbox>
    </object>
</annotation>
